atlassian/VERSION
atlassian/__init__.py
atlassian/bamboo.py
atlassian/bitbucket.py
atlassian/confluence.py
atlassian/crowd.py
atlassian/jira.py
atlassian/portfolio.py
atlassian/rest_client.py
atlassian/service_desk.py
atlassian/utils.py
tests/__init__.py
tests/test_base.py
atlassian_python_api_cti-1.12.0.dist-info/LICENSE
atlassian_python_api_cti-1.12.0.dist-info/METADATA
atlassian_python_api_cti-1.12.0.dist-info/WHEEL
atlassian_python_api_cti-1.12.0.dist-info/top_level.txt
atlassian_python_api_cti-1.12.0.dist-info/RECORD
